pk_model/Block_pulse_dose.py
pk_model/__init__.py
pk_model/abstractDataCollector.py
pk_model/abstractModel.py
pk_model/abstractParameters.py
pk_model/abstractPlotter.py
pk_model/api.py
pk_model/dataCollector_factory.py
pk_model/dataCollectors/dataCollector_numpy.py
pk_model/model_factory.py
pk_model/models/iv_model_bckEuler.py
pk_model/models/iv_model_ncompt_scipy.py
pk_model/models/iv_model_scipy.py
pk_model/models/sub_model_bckEuler.py
pk_model/models/sub_model_ncompt_scipy.py
pk_model/models/sub_model_scipy.py
pk_model/parameters/iv_nCompartment_parameters.py
pk_model/parameters/parameters_iv.py
pk_model/parameters/parameters_sub.py
pk_model/parameters/sub_nCompartment_parameters.py
pk_model/parameters_factory.py
pk_model/params.json
pk_model/params.txt
pk_model/plotter_factory.py
pk_model/plotters/plotFromCSV.py
pk_model/plotters/plotFromConfig.py
pk_model/tests/__init__.py
pk_model/tests/config.py
pk_model/tests/test_abstractClasses.py
pk_model/tests/test_api.py
pk_model/tests/test_dataCollectors.py
pk_model/tests/test_doseFns.py
pk_model/tests/test_model_basic.py
pk_model/tests/test_model_comparisons.py
pk_model/tests/test_parameters.py
pk_model/version_info.py
pk_model-0.1.6.dist-info/LICENSE
pk_model-0.1.6.dist-info/WHEEL
pk_model-0.1.6.dist-info/METADATA
pk_model-0.1.6.dist-info/RECORD
