Metadata-Version: 2.1
Name: pk-model
Version: 0.1.6
Summary: Basic Pharmokinetic Model
License: "MIT"
Author: Kit Gallagher
Author-email: gallagherkit@outlook.com
Requires-Python: >=3.8,<3.10
Classifier: License :: Other/Proprietary License
Classifier: Programming Language :: Python :: 3
Classifier: Programming Language :: Python :: 3.8
Classifier: Programming Language :: Python :: 3.9
Requires-Dist: matplotlib (>=3.4.3,<4.0.0)
Requires-Dist: numpy (>=1.20.0,<1.21.0)
Requires-Dist: pandas (>=1.3.4,<2.0.0)
Requires-Dist: scipy (>=1.7.1,<2.0.0)
